[
  {
    "title": "Кто мы?",
    "text": "<p>Мы создаем пространство для всестороннего  развития личности в любом возрасте.</p>"
  },
  {
    "title": "Зачем мы?",
    "text": "<p>Знание и понимание своих личных способностей и одаренностей круто поможет повысить свой потенциал и максимально реализоваться в жизни.</p>"
  },
  {
    "title": "Почему мы?",
    "text": "<p>С помощью тестов ты определишь свои способности и сможешь прокачаться в разных направлениях: музыкальном, рисовании, пении, актерском мастерстве, программировании, понимании своего тела, умении коммуницировать.</p>"
  },
  {
    "title": "Когда мы?",
    "text": "<p>Как можно раньше - чем раньше ты начнешь повышать свой потенциал, тем быстрее изменится твоя жизнь.</p>"
  }
]